funcmasker_flex/config/snakebids.yml
funcmasker_flex/pipeline_description.json
funcmasker_flex/resources/template.json
funcmasker_flex/resources/test_subjects.txt
funcmasker_flex/resources/train_subjects.txt
funcmasker_flex/run.py
funcmasker_flex/workflow/Snakefile
funcmasker_flex/workflow/rules/common.smk
funcmasker_flex/workflow/rules/evaluate.smk
funcmasker_flex/workflow/rules/evaluate_rutherford.smk
funcmasker_flex/workflow/rules/inference.smk
funcmasker_flex/workflow/rules/training.smk
funcmasker_flex/workflow/scripts/create_json.py
funcmasker_flex-0.2.0.dist-info/entry_points.txt
funcmasker_flex-0.2.0.dist-info/WHEEL
funcmasker_flex-0.2.0.dist-info/METADATA
funcmasker_flex-0.2.0.dist-info/RECORD
